autopep8.py
hlautopep8-1.5a1.dist-info/AUTHORS.rst
hlautopep8-1.5a1.dist-info/LICENSE
hlautopep8-1.5a1.dist-info/METADATA
hlautopep8-1.5a1.dist-info/WHEEL
hlautopep8-1.5a1.dist-info/entry_points.txt
hlautopep8-1.5a1.dist-info/top_level.txt
hlautopep8-1.5a1.dist-info/RECORD
