Metadata-Version: 2.1
Name: hlautopep8
Version: 1.5a1
Summary: A tool that automatically formats Python code to conform to the PEP 8 style guide
Home-page: https://github.com/hhatto/autopep8
Author: Hideo Hattori
Author-email: hhatto.jp@gmail.com
License: Expat License
Keywords: automation,pep8,format,pycodestyle
Platform: UNKNOWN
Classifier: Development Status :: 5 - Production/Stable
Classifier: Environment :: Console
Classifier: Intended Audience :: Developers
Classifier: License :: OSI Approved :: MIT License
Classifier: Operating System :: OS Independent
Classifier: Programming Language :: Python
Classifier: Programming Language :: Python :: 2
Classifier: Programming Language :: Python :: 2.7
Classifier: Programming Language :: Python :: 3
Classifier: Programming Language :: Python :: 3.4
Classifier: Programming Language :: Python :: 3.5
Classifier: Programming Language :: Python :: 3.6
Classifier: Programming Language :: Python :: 3.7
Classifier: Topic :: Software Development :: Libraries :: Python Modules
Classifier: Topic :: Software Development :: Quality Assurance
Requires-Dist: pycodestyle (>=2.5.0)
